{
  "name": "dex",
  "tree": {
    "$className": "DataModel",
    "Workspace": {
      "$properties": {
        "SignalBehavior": "Immediate"
      }
    },
    "ReplicatedStorage": {
      "Packages": {
        "$className": "Folder",
        "Dex": {
          "$path": "src"
        }
      },
      "DevPackages": {
        "$path": "DevPackages"
      },
      "DexTests": {
        "$path": "tests"
      }
    },
    "ServerScriptService":{
      "TestRunner": {
        "$path": "workflowtools/TestRunner.server.luau"
      }
    }
  }
}